django_mail_admin/__init__.py
django_mail_admin/admin.py
django_mail_admin/apps.py
django_mail_admin/backends.py
django_mail_admin/cache.py
django_mail_admin/connections.py
django_mail_admin/fields.py
django_mail_admin/forms.py
django_mail_admin/google_utils.py
django_mail_admin/lockfile.py
django_mail_admin/logutils.py
django_mail_admin/mail.py
django_mail_admin/settings.py
django_mail_admin/signals.py
django_mail_admin/urls.py
django_mail_admin/utils.py
django_mail_admin/validators.py
django_mail_admin/views.py
django_mail_admin/management/__init__.py
django_mail_admin/management/commands/__init__.py
django_mail_admin/management/commands/cleanup_email.py
django_mail_admin/management/commands/get_new_mail.py
django_mail_admin/management/commands/send_queued_mail.py
django_mail_admin/migrations/0001_initial.py
django_mail_admin/migrations/0002_auto_20190709_1139.py
django_mail_admin/migrations/__init__.py
django_mail_admin/models/__init__.py
django_mail_admin/models/configurations.py
django_mail_admin/models/incoming.py
django_mail_admin/models/logs.py
django_mail_admin/models/outgoing.py
django_mail_admin/models/templates.py
django_mail_admin/transports/__init__.py
django_mail_admin/transports/babyl.py
django_mail_admin/transports/base.py
django_mail_admin/transports/generic.py
django_mail_admin/transports/gmail.py
django_mail_admin/transports/imap.py
django_mail_admin/transports/maildir.py
django_mail_admin/transports/mbox.py
django_mail_admin/transports/mh.py
django_mail_admin/transports/mmdf.py
django_mail_admin/transports/pop3.py
django_mail_admin-0.3.2.dist-info/DESCRIPTION.rst
django_mail_admin-0.3.2.dist-info/METADATA
django_mail_admin-0.3.2.dist-info/RECORD
django_mail_admin-0.3.2.dist-info/WHEEL
django_mail_admin-0.3.2.dist-info/metadata.json
django_mail_admin-0.3.2.dist-info/top_level.txt
