Metadata-Version: 2.0
Name: django-mail-admin
Version: 0.3.2
Summary: The one and only django app to receive & send mail with templates and multiple configurations.
Home-page: https://github.com/delneg/django_mail_admin
Author: Denis Bobrov
Author-email: delneg@yandex.ru
License: MIT
Keywords: django_mail_admin
Platform: UNKNOWN
Classifier: Development Status :: 3 - Alpha
Classifier: Framework :: Django
Classifier: Framework :: Django :: 1.9
Classifier: Framework :: Django :: 1.10
Classifier: Framework :: Django :: 1.11
Classifier: Framework :: Django :: 2.0
Classifier: Framework :: Django :: 3.0
Classifier: Framework :: Django :: 4.0
Classifier: Intended Audience :: Developers
Classifier: License :: OSI Approved :: BSD License
Classifier: Natural Language :: English
Classifier: Programming Language :: Python :: 3
Classifier: Programming Language :: Python :: 3.5
Classifier: Programming Language :: Python :: 3.6
Classifier: Programming Language :: Python :: 3.7
Classifier: Programming Language :: Python :: 3.8
Classifier: Programming Language :: Python :: 3.9
Classifier: Programming Language :: Python :: 3.10
Classifier: Programming Language :: Python :: 3.11
Provides-Extra: gmail
License-File: LICENSE
License-File: AUTHORS.rst
Requires-Dist: jsonfield
Provides-Extra: gmail
Requires-Dist: social-auth-app-django; extra == 'gmail'
